lastfm_vk_download/__init__.py
lastfm_vk_download/decode.js
lastfm_vk_download/download_from_vk.py
lastfm_vk_download/htmldecode
lastfm_vk_download/lastfm_to_json.py
lastfm_vk_download/urlencode
lastfm_vk_download/vkfindaudio-w3m
lastfm_vk_download-1.0.0.dist-info/DESCRIPTION.rst
lastfm_vk_download-1.0.0.dist-info/METADATA
lastfm_vk_download-1.0.0.dist-info/RECORD
lastfm_vk_download-1.0.0.dist-info/WHEEL
lastfm_vk_download-1.0.0.dist-info/entry_points.txt
lastfm_vk_download-1.0.0.dist-info/metadata.json
lastfm_vk_download-1.0.0.dist-info/top_level.txt
