Metadata-Version: 2.0
Name: lastfm-vk-download
Version: 1.0.0
Summary: Get user's top tracks from lastfm and download them from vk.com
Home-page: https://github.com/philip-bl/lastfm_vk_download
Author: Philip Blagoveschensky
Author-email: me@crabman.me
License: MIT
Platform: UNKNOWN
Classifier: Programming Language :: Python
Classifier: Programming Language :: Python :: 3
Classifier: Programming Language :: Python :: 3.5
Classifier: License :: OSI Approved :: MIT License
Classifier: Operating System :: POSIX
Classifier: Development Status :: 4 - Beta
Classifier: Topic :: Utilities
Requires-Dist: click (>=6.7)
Requires-Dist: libcrap (>=0.2.4)
Requires-Dist: path.py (>=10.1)
Requires-Dist: plumbum (>=1.6.3)
Requires-Dist: requests (>=2.13)
Requires-Dist: wget (>=3.2)
